MANIFEST.in
README.rst
setup.py
rawimg/__init__.py
rawimg/cli.py
rawimg.egg-info/PKG-INFO
rawimg.egg-info/SOURCES.txt
rawimg.egg-info/dependency_links.txt
rawimg.egg-info/entry_points.txt
rawimg.egg-info/requires.txt
rawimg.egg-info/top_level.txt