Metadata-Version: 1.0
Name: rawimg
Version: 0.0.2
Summary: UNKNOWN
Home-page: UNKNOWN
Author: SATO Naoya
Author-email: s@tonaoya.com
License: MIT
Platform: UNKNOWN
Classifier: Development Status :: 4 - Beta
Classifier: Intended Audience :: Developers
Classifier: Natural Language :: English
Classifier: License :: OSI Approved :: MIT License
Classifier: Programming Language :: Python
Classifier: Programming Language :: Python :: 2.6
Classifier: Programming Language :: Python :: 2.7
